unidic_combo/__init__.py
unidic_combo/config.template.jsonnet
unidic_combo/main.py
unidic_combo/predict.py
unidic_combo/unidic_combo.py
unidic_combo/commands/__init__.py
unidic_combo/commands/train.py
unidic_combo/data/__init__.py
unidic_combo/data/api.py
unidic_combo/data/dataset.py
unidic_combo/data/fields/__init__.py
unidic_combo/data/fields/sequence_multilabel_field.py
unidic_combo/data/samplers/__init__.py
unidic_combo/data/samplers/samplers.py
unidic_combo/data/token_indexers/__init__.py
unidic_combo/data/token_indexers/pretrained_transformer_mismatched_indexer.py
unidic_combo/data/token_indexers/token_characters_indexer.py
unidic_combo/data/token_indexers/token_features_indexer.py
unidic_combo/download/filesize.txt
unidic_combo/models/__init__.py
unidic_combo/models/base.py
unidic_combo/models/dilated_cnn.py
unidic_combo/models/embeddings.py
unidic_combo/models/encoder.py
unidic_combo/models/graph_parser.py
unidic_combo/models/lemma.py
unidic_combo/models/model.py
unidic_combo/models/morpho.py
unidic_combo/models/parser.py
unidic_combo/models/utils.py
unidic_combo/training/__init__.py
unidic_combo/training/checkpointer.py
unidic_combo/training/scheduler.py
unidic_combo/training/tensorboard_writer.py
unidic_combo/training/trainer.py
unidic_combo/utils/__init__.py
unidic_combo/utils/checks.py
unidic_combo/utils/download.py
unidic_combo/utils/graph.py
unidic_combo/utils/metrics.py
unidic_combo-1.5.4.dist-info/LICENSE.txt
unidic_combo-1.5.4.dist-info/METADATA
unidic_combo-1.5.4.dist-info/WHEEL
unidic_combo-1.5.4.dist-info/top_level.txt
unidic_combo-1.5.4.dist-info/RECORD
