Metadata-Version: 2.1
Name: unidic-combo
Version: 1.5.4
Summary: UniDic2UD + COMBO-pytorch wrapper for spaCy
Home-page: https://github.com/KoichiYasuoka/UniDic-COMBO
Author: Koichi Yasuoka
Author-email: yasuoka@kanji.zinbun.kyoto-u.ac.jp
License: GPL
Project-URL: COMBO-pytorch, https://gitlab.clarin-pl.eu/syntactic-tools/combo
Project-URL: Source, https://github.com/KoichiYasuoka/UniDic-COMBO
Project-URL: Tracker, https://github.com/KoichiYasuoka/UniDic-COMBO/issues
Keywords: NLP Japanese spaCy
Classifier: License :: OSI Approved :: GNU General Public License (GPL)
Classifier: Programming Language :: Python :: 3
Classifier: Operating System :: OS Independent
Classifier: Topic :: Text Processing :: Linguistic
Classifier: Natural Language :: Japanese
Requires-Python: >=3.6
License-File: LICENSE.txt
Requires-Dist: absl-py (>=0.9.0)
Requires-Dist: conllu (>=2.3.2)
Requires-Dist: dataclasses-json (>=0.5.2)
Requires-Dist: fugashi (>=1.3.3)
Requires-Dist: ipadic (>=1.0.0)
Requires-Dist: protobuf (>=3.14.0)
Requires-Dist: requests (>=2.23.0)
Requires-Dist: spacy (>=2.2.2)
Requires-Dist: torch (>=1.6.0)
Requires-Dist: transformers (<4.31)
Requires-Dist: unidic-lite (>=1.0.8)
Requires-Dist: unidic2ud (>=3.0.7)
